topsis/__init__.py
topsis/__main__.py
topsis_amisha_102117166-1.1.0.dist-info/METADATA
topsis_amisha_102117166-1.1.0.dist-info/WHEEL
topsis_amisha_102117166-1.1.0.dist-info/entry_points.txt
topsis_amisha_102117166-1.1.0.dist-info/top_level.txt
topsis_amisha_102117166-1.1.0.dist-info/RECORD
