Metadata-Version: 2.1
Name: topsis-amisha-102117166
Version: 1.1.0
Summary: It gives the ranking to models as per the TOPSIS score.Please view the instructions so as to run the package smoothly in your terminal.
Author: Amisha
Author-email: aamisha_be21@thapar.edu
License: MIT
Classifier: License :: OSI Approved :: MIT License
Classifier: Programming Language :: Python :: 3.6
Classifier: Programming Language :: Python :: 3.7
Classifier: Programming Language :: Python :: 3.8
